dream_on_gym_v2-0.0.9.dist-info/licenses/COPYING.md
dreamongymv2/gym_basic/__init__.py
dreamongymv2/gym_basic/envs/__init__.py
dreamongymv2/gym_basic/envs/rl_on_env.py
dreamongymv2/simNetPy/__init__.py
dreamongymv2/simNetPy/bitRate.py
dreamongymv2/simNetPy/connection.py
dreamongymv2/simNetPy/connectionEvent.py
dreamongymv2/simNetPy/controller.py
dreamongymv2/simNetPy/event.py
dreamongymv2/simNetPy/event_finite.py
dreamongymv2/simNetPy/expVariable.py
dreamongymv2/simNetPy/link.py
dreamongymv2/simNetPy/network.py
dreamongymv2/simNetPy/node.py
dreamongymv2/simNetPy/randomVariable.py
dreamongymv2/simNetPy/simulator.py
dreamongymv2/simNetPy/simulator_finite.py
dreamongymv2/simNetPy/uniformVariable.py
dreamongymv2/simNetPy/filemanager/__init__.py
dreamongymv2/simNetPy/filemanager/readerJson.py
dream_on_gym_v2-0.0.9.dist-info/METADATA
dream_on_gym_v2-0.0.9.dist-info/WHEEL
dream_on_gym_v2-0.0.9.dist-info/top_level.txt
dream_on_gym_v2-0.0.9.dist-info/RECORD
